{"name":"build-javascript","namedChunkGroups":{"polyfill":{"name":"polyfill","assets":[{"name":"webpack-runtime-f175f29ae549f0c214fc.js","size":3272},{"name":"polyfill-3c61b1312c989de525e4.js","size":85009}],"filteredAssets":0,"assetsSize":88281,"filteredAuxiliaryAssets":2,"auxiliaryAssetsSize":224149},"app":{"name":"app","assets":[{"name":"webpack-runtime-f175f29ae549f0c214fc.js","size":3272},{"name":"framework-b2da9b3e4373cc597661.js","size":140536},{"name":"styles.a84dfcc43c30f0e3598c.css","size":9210},{"name":"app-dd9abe2896c1888c7060.js","size":79195}],"filteredAssets":0,"assetsSize":232213,"filteredAuxiliaryAssets":3,"auxiliaryAssetsSize":701005},"component---src-pages-404-tsx":{"name":"component---src-pages-404-tsx","assets":[{"name":"commons-3720178fda057b2a1949.js","size":18080},{"name":"component---src-pages-404-tsx-dc32051fe03d22e6dcf8.js","size":2341}],"filteredAssets":0,"assetsSize":20421,"filteredAuxiliaryAssets":2,"auxiliaryAssetsSize":59606},"component---src-pages-index-tsx":{"name":"component---src-pages-index-tsx","assets":[{"name":"commons-3720178fda057b2a1949.js","size":18080},{"name":"component---src-pages-index-tsx-0b2ede975e8b900818cd.js","size":13445}],"filteredAssets":0,"assetsSize":31525,"filteredAuxiliaryAssets":2,"auxiliaryAssetsSize":94659}},"assetsByChunkName":{"polyfill":["webpack-runtime-f175f29ae549f0c214fc.js","polyfill-3c61b1312c989de525e4.js"],"app":["webpack-runtime-f175f29ae549f0c214fc.js","framework-b2da9b3e4373cc597661.js","styles.a84dfcc43c30f0e3598c.css","app-dd9abe2896c1888c7060.js"],"component---src-pages-404-tsx":["commons-3720178fda057b2a1949.js","component---src-pages-404-tsx-dc32051fe03d22e6dcf8.js"],"component---src-pages-index-tsx":["commons-3720178fda057b2a1949.js","component---src-pages-index-tsx-0b2ede975e8b900818cd.js"]},"childAssetsByChunkName":{}}