{"name":"build-javascript","namedChunkGroups":{"polyfill":{"name":"polyfill","assets":[{"name":"webpack-runtime-73dcfc839ca38c3ed34a.js","size":3272},{"name":"polyfill-3c61b1312c989de525e4.js","size":85009}],"filteredAssets":0,"assetsSize":88281,"filteredAuxiliaryAssets":2,"auxiliaryAssetsSize":224149},"app":{"name":"app","assets":[{"name":"webpack-runtime-73dcfc839ca38c3ed34a.js","size":3272},{"name":"framework-b2da9b3e4373cc597661.js","size":140536},{"name":"styles.afbcb96c82d7574e0e8c.css","size":11674},{"name":"app-0807c0cc385e943a24d1.js","size":79194}],"filteredAssets":0,"assetsSize":234676,"filteredAuxiliaryAssets":3,"auxiliaryAssetsSize":701005},"component---src-pages-404-tsx":{"name":"component---src-pages-404-tsx","assets":[{"name":"commons-0536081e3cebf35ea491.js","size":25135},{"name":"component---src-pages-404-tsx-1b995985de87d8cf94ad.js","size":2428}],"filteredAssets":0,"assetsSize":27563,"filteredAuxiliaryAssets":2,"auxiliaryAssetsSize":81992},"component---src-pages-index-tsx":{"name":"component---src-pages-index-tsx","assets":[{"name":"commons-0536081e3cebf35ea491.js","size":25135},{"name":"component---src-pages-index-tsx-5c397c4e77111e390908.js","size":16207}],"filteredAssets":0,"assetsSize":41342,"filteredAuxiliaryAssets":2,"auxiliaryAssetsSize":125471}},"assetsByChunkName":{"polyfill":["webpack-runtime-73dcfc839ca38c3ed34a.js","polyfill-3c61b1312c989de525e4.js"],"app":["webpack-runtime-73dcfc839ca38c3ed34a.js","framework-b2da9b3e4373cc597661.js","styles.afbcb96c82d7574e0e8c.css","app-0807c0cc385e943a24d1.js"],"component---src-pages-404-tsx":["commons-0536081e3cebf35ea491.js","component---src-pages-404-tsx-1b995985de87d8cf94ad.js"],"component---src-pages-index-tsx":["commons-0536081e3cebf35ea491.js","component---src-pages-index-tsx-5c397c4e77111e390908.js"]},"childAssetsByChunkName":{}}